flatfilecms/__init__.py
flatfilecms/events.py
flatfilecms/filters.py
flatfilecms/models.py
flatfilecms/resources.py
flatfilecms/routes.py
flatfilecms/templates/404.jinja2
flatfilecms/templates/amp-counter.jinja2
flatfilecms/templates/amp.jinja2
flatfilecms/templates/atom.jinja2
flatfilecms/templates/base.jinja2
flatfilecms/templates/blogpost.jinja2
flatfilecms/templates/blogposts.jinja2
flatfilecms/templates/counter.jinja2
flatfilecms/templates/default.jinja2
flatfilecms/templates/feedlinks.jinja2
flatfilecms/templates/footer.jinja2
flatfilecms/templates/header.jinja2
flatfilecms/templates/home.jinja2
flatfilecms/templates/layout.jinja2
flatfilecms/templates/logo.jinja2
flatfilecms/templates/macros.jinja2
flatfilecms/templates/onepage.jinja2
flatfilecms/templates/service.jinja2
flatfilecms/templates/sitemap.jinja2
flatfilecms/templates/solution.jinja2
flatfilecms/templates/bootstrap/blockquote.jinja2
flatfilecms/templates/bootstrap/fullscreen-jumbotron.jinja2
flatfilecms/views/__init__.py
flatfilecms/views/notfound.py
flatfilecms/views/pages.py
flatfilecms-0.3.dist-info/METADATA
flatfilecms-0.3.dist-info/RECORD
flatfilecms-0.3.dist-info/WHEEL
flatfilecms-0.3.dist-info/entry_points.txt
flatfilecms-0.3.dist-info/top_level.txt
tests/__init__.py
tests/conftest.py
tests/test_events.py
tests/test_pages.py
tests/views.py
