Metadata-Version: 2.1
Name: flatfilecms
Version: 0.3
Summary: flat-file CMS suitable for static site
Home-page: https://trac.radium.group/flatfilecms/
Author: Anton Kasimov
Author-email: kasimov@radium-it.ru
License: UNKNOWN
Keywords: web pyramid pylons flat-file CMS
Platform: UNKNOWN
Classifier: Programming Language :: Python
Classifier: Framework :: Pyramid
Classifier: Topic :: Internet :: WWW/HTTP
Classifier: Topic :: Internet :: WWW/HTTP :: WSGI :: Application
Provides-Extra: testing
Requires-Dist: plaster-pastedeploy
Requires-Dist: pyramid (>=1.10)
Requires-Dist: pyramid-debugtoolbar
Requires-Dist: pyramid-jinja2
Requires-Dist: pyramid-retry
Requires-Dist: pyramid-tm
Requires-Dist: transaction
Requires-Dist: waitress
Requires-Dist: Markdown
Requires-Dist: PyYAML
Requires-Dist: python-frontmatter
Requires-Dist: pyramid-htmlmin
Requires-Dist: pyramid-webpack
Requires-Dist: Babel
Provides-Extra: testing
Requires-Dist: WebTest (>=1.3.1); extra == 'testing'
Requires-Dist: pytest; extra == 'testing'
Requires-Dist: pytest-cov; extra == 'testing'
